{
  "document_info": {
    "document_type": "Quyết định thi hành án",
    "case_number": "1161/2025/Q",
    "court_name": "TÒA ÁN NHÂN DÂN CỘNG HÒA XÃ HỘI CHỦ NGHĨA VIỆT NAM THÀNH PHÓ THỦ ĐỨC Độc lập - Tự đo — Hạnh phúc THÀNH PHÓ HÒ CHÍ MINH Số: 1161/2025/QĐST-DS Thành phá Thủ Đức, ngày 30 tháng 6 năm 2025 QUYẾT ĐỊNH CÔNG NHẬN SỰ THỎA THUẬN CỦA CÁC ĐƯƠNG SỰ Căn cứ vào Điều 212 và Điều 213 của Bộ luật Tổ tụng dân sự, Căn cứ Bộ luật dân sự năm 2015; Căn cứ vào Diều 26 Nghị quyết số 326/2016/UBTVQH14 ngày 30 tháng 12 năm 2016 của Ủy ban Thường vụ Quốc Hội quy định về mức thu, miễn, giảm, thu, nộp, quản lý và sử dựng án phí và lệ phí Tòa án, C*n cứ vào biên bản hoà giải thành ngày 20 tháng 6 năm 2025 về việc các đương sự thoả thuận được với nhau về việc giải quyết toàn bộ vụ án dân sự thụ lý số 447/2022/TLST-DS ngày o] thắng 6 năm 2022 về việc “Tranh chấp hợp động tín dựng ”. XÉT THÁY: Các thoả thuận của các đương sự được ghí trong biên bản boà giải thành về việc giải quyết toàn bộ vụ án là tự nguyện, nội dung thoả thuận giữa đương sự không vi phạm Điều cắm của luật và không trái đạo đức xã hội. Đã hết thời hạn 07 ngày, kể từ ngày lập biên bản hòa giải thành, không có \\ đương sự nào thay đổi ý kiến về sự thoả thuận đó. QUYÉT ĐỊNH: I. Công nhận sự thoả thuận của các đương sự: Nguyên đơn: Ngân hàng Thương mại Cổ Phần Quốc Dân; Trụ sở: số 25 Lê Đại Hành, phường Lê Đại Hành, quận Hai Bà Trưng, Thành phế Hà Nội; Người đại diện theo ủy quyền: Bà Nguyễn Thị Mỹ Linh; Địa chỉ: số 151-153 Nguyễn Đình Chiểu, Phường Võ Thị Sáu, Quận 3, Thành phố Hồ Chí Minh; Giấy ủy quyền số 4346/2025/UQ-NCB ngày 19/6/2025. Bị đơn: Ông Trần Trùng Sinh, sinh năm 1977; Địa chỉ: 605 chung cư 1C1 ( A1-705) Cantavil, phường An Phú, thành phố Thủ Đức, Thành phố Hồ Chí Minh; Người có quyền lợi, nghĩa vụ liên quan: Công ty CỔ Phần Đầu tư ~ Thương mại - Dịch vụ Việt Úc; Trụ sở: Tẳng B, tòa nhà Pearl Plaza, số 561 Điện Biên Phủ, Phường 25, quận Bình Thạnh, Thành phỏ Hồ Chí Minh;",
    "date_issued": "19/6/2025",
    "parties": {
      "defendants": [
        "Ông Trần Trùng Sinh, sinh năm 1977"
      ],
      "plaintiffs": [
        "Ngân hàng Thương mại Cổ Phần Quốc Dân"
      ],
      "prosecutors": [],
      "judges": []
    },
    "charges": [],
    "verdict": "CÔNG NHẬN SỰ THỎA THUẬN CỦA CÁC ĐƯƠNG SỰ Căn cứ vào Điều 212 và Điều 213 của Bộ luật Tổ tụng dân sự, Căn cứ Bộ luật dân sự năm 2015; Căn cứ vào Diều 26 Nghị quyết số 326/2016/UBTVQH14 ngày 30 tháng 12 năm 2016 của Ủy ban Thường vụ Quốc Hội quy định về mức thu, miễn, giảm, thu, nộp, quản lý và sử dựng án phí và lệ phí Tòa án, C*n cứ vào biên bản hoà giải thành ngày 20 tháng 6 năm 2025 về việc các đương sự thoả thuận được với nhau về việc giải quyết toàn bộ vụ án dân sự thụ lý số 447/2022/TLST-DS ngày o] thắng 6 năm 2022 về việc “Tranh chấp hợp động tín dựng ”. XÉT THÁY: Các thoả thuận của các đương sự được ghí trong biên bản boà giải thành về việc giải quyết toàn bộ vụ án là tự nguyện, nội dung thoả thuận giữa đương sự không vi phạm Điều cắm của luật và không trái đạo đức xã hội. Đã hết thời hạn 07 ngày, kể từ ngày lập biên bản hòa giải thành, không có \\ đương sự nào thay đổi ý kiến về sự thoả thuận đó. QUYÉT ĐỊNH: I. Công nhận sự thoả thuận của các đương sự: Nguyên đơn: Ngân hàng Thương mại Cổ Phần Quốc Dân; Trụ sở: số 25 Lê Đại Hành, phường Lê Đại Hành, quận Hai Bà Trưng, Thành phế Hà Nội; Người đại diện theo ủy quyền: Bà Nguyễn Thị Mỹ Linh; Địa chỉ: số 151-153 Nguyễn Đình Chiểu, Phường Võ Thị Sáu, Quận 3, Thành phố Hồ Chí Minh; Giấy ủy quyền số 4346/2025/UQ-NCB ngày 19/6/2025. Bị đơn: Ông Trần Trùng Sinh, sinh năm 1977; Địa chỉ: 605 chung cư 1C1 ( A1-705) Cantavil, phường An Phú, thành phố Thủ Đức, Thành phố Hồ Chí Minh; Người có quyền lợi, nghĩa vụ liên quan: Công ty CỔ Phần Đầu tư ~ Thương mại - Dịch vụ Việt Úc; Trụ sở: Tẳng B, tòa nhà Pearl Plaza, số 561 Điện Biên Phủ, Phường 25, quận Bình Thạnh, Thành phỏ Hồ Chí Minh;",
    "sentence": null,
    "legal_references": [
      "Điều 2",
      "Điều 6",
      "Điều 212",
      "Điều 213",
      "Bộ luật Tổ tụng dân sự, Căn cứ Bộ luật dân sự năm 2015"
    ],
    "key_facts": []
  },
  "processing_timestamp": "2025-09-23T14:08:27.812839",
  "confidence_score": 0.75
}