{
  "document_info": {
    "document_type": "Bản án dân sự",
    "case_number": "67/2025/Q",
    "court_name": "TÒA ÁN NHÂN DÂN CỘNG HÒA XÃ HỘI CHỦ NGHĨA VIỆT NAM THÀNH PHÓ HÒ CHÍ MINH Độc lập — Tự do —- Hạnh phúc Số: 67/2025/QĐ-PT Thành phá HỖ Chí Minh, ngày 20 tháng s năm 2025 i QUYẾT ĐỊNH HỦY BẢN ÁN SƠ THẢM VÀ ĐÌNH CHỈ GIẢI QUYẾT VỤ ÁN DÂN SỰ TÒA ÁN NHÂN DÂN THÀNH PHÓ HÒ CHÍ MINH Với Hội đồng xét rử phúc thẳm gồm có: Thẩm phán - Chủ toạ phiên tcz: ng Hỗ Minh Cường. Các Thẩm phán: Bà Võ Thị Mỹ Hạnh; Ông Phan Trịnh Minh Đức. Sau Khí xét xử sơ Cấm, Bản ín hôn nhân và gia đình sơ thẩm số 2382/2024/HNGĐ-ST mấy 11 tháng 2 - cúi 2024 vuằ vứt ác Thân 2 phố Thủ Đức, Thành hỗ HÀ < 2: tinh bị kháng cáo như sau: M3 ^^m-24, bà Nguyễn Ngọc Xuân An kháng cáo quá hạn, yêu cầu: tòa án cắp phúc thẳm xem xét sửa án sơ thẩm theo hướng bác yêu cầu khởi kiện của ông Đặng Vũ Tắn hoặc hủy án sơ thẩm do án sơ thẩm xét xử không khách quan, vi phạm nghiêm trọng thủ tục tố tựng, làm ảnh hưởng quyền, lợi ích hợp pháp của mẹ con bà. ngày 20/12/2024, Tòa án nhân dân thành phố Hồ Chí Minh ban hành Quyết định chấp nhận việc kháng cáo quá hạn số 102/2024/QĐ-PT, chấp nhận kháng cáo quá hẹn của bà Án. XÉT THÁY: Tại phiên tòa phúc thắm, ông Đặng Vũ Tắn có đơn xin rút toàn bộ yêu cầu khởi kiện, bả Lê Thị Thanh Tuyển là đại diện theo ủy quyển của bị đơn — bà Nguyễn Ngọc Xuân An có đơn xin rút toàn bộ yêu cầu kháng cáo. Căn cứ Điều 289, Điều 295 của Bộ luật Tố tụng dân sự, QUYẾT ĐỊNH: I, Hủy Bản án hôn nhân và gia đình sơ thẩm số 2382/2024/HNGĐ-ST ngày 11 tháng 6 năm 2024 của Tòa án nhân dân thành phố Thủ Đức, Thành phố Hồ Chí Minh và đình chỉ giải quyết vụ án dân sự phúc thẩm thụ lý số 48/2025/TLPT-HNGĐ ngày 17 tháng 3 năm 2025 về việc “Tranh chấp thay đổi người trực tiếp nuôi con sau khi ly hôn”, giữa: Nguyên đơn: Ông Đặng Vũ Tín, sinh năm 1981.",
    "date_issued": "20/12/2024",
    "parties": {
      "defendants": [
        "— bà Nguyễn Ngọc Xuân An có đơn xin rút toàn bộ yêu cầu kháng cáo. Căn cứ Điều 289, Điều 295 của Bộ luật Tố tụng dân sự, QUYẾT ĐỊNH: I, Hủy Bản án hôn nhân và gia đình sơ thẩm số 2382/2024/HNGĐ-ST ngày 11 tháng 6 năm 2024 của Tòa án nhân dân thành phố Thủ Đức, Thành phố Hồ Chí Minh và đình chỉ giải quyết vụ án dân sự phúc thẩm thụ lý số 48/2025/TLPT-HNGĐ ngày 17 tháng 3 năm 2025 về việc “Tranh chấp thay đổi người trực tiếp nuôi con sau khi ly hôn”, giữa: Nguyên đơn: Ông Đặng Vũ Tín, sinh năm 1981.",
        "Bà Nguyễn Ngọc Xuân An, sinh năm 1988. Địa chỉ: 24/12 Trịnh Khắc Lập, phường Thạnh Mỹ Lợi, thành phố Thủ Đức, Thành phố Hồ Chí Minh. Người đại diện theo ủy quyền của bị đơn: Bả Lê Thị Thanh Tuyển, sinh năm 1977"
      ],
      "plaintiffs": [
        "Ông Đặng Vũ Tín, sinh năm 1981."
      ],
      "prosecutors": [],
      "judges": [
        "- Chủ toạ phiên tcz: ng Hỗ Minh Cường. Các Thẩm phán: Bà Võ Thị Mỹ Hạnh"
      ]
    },
    "charges": [],
    "verdict": "HỦY BẢN ÁN SƠ THẢM VÀ ĐÌNH CHỈ GIẢI QUYẾT VỤ ÁN DÂN SỰ TÒA ÁN NHÂN DÂN THÀNH PHÓ HÒ CHÍ MINH Với Hội đồng xét rử phúc thẳm gồm có: Thẩm phán - Chủ toạ phiên tcz: ng Hỗ Minh Cường. Các Thẩm phán: Bà Võ Thị Mỹ Hạnh; Ông Phan Trịnh Minh Đức. Sau Khí xét xử sơ Cấm, Bản ín hôn nhân và gia đình sơ thẩm số 2382/2024/HNGĐ-ST mấy 11 tháng 2 - cúi 2024 vuằ vứt ác Thân 2 phố Thủ Đức, Thành hỗ HÀ < 2: tinh bị kháng cáo như sau: M3 ^^m-24, bà Nguyễn Ngọc Xuân An kháng cáo quá hạn, yêu cầu: tòa án cắp phúc thẳm xem xét sửa án sơ thẩm theo hướng bác yêu cầu khởi kiện của ông Đặng Vũ Tắn hoặc hủy án sơ thẩm do án sơ thẩm xét xử không khách quan, vi phạm nghiêm trọng thủ tục tố tựng, làm ảnh hưởng quyền, lợi ích hợp pháp của mẹ con bà. ngày 20/12/2024, Tòa án nhân dân thành phố Hồ Chí Minh ban hành Quyết định chấp nhận việc kháng cáo quá hạn số 102/2024/QĐ-PT, chấp nhận kháng cáo quá hẹn của bà Án. XÉT THÁY: Tại phiên tòa phúc thắm, ông Đặng Vũ Tắn có đơn xin rút toàn bộ yêu cầu khởi kiện, bả Lê Thị Thanh Tuyển là đại diện theo ủy quyển của bị đơn — bà Nguyễn Ngọc Xuân An có đơn xin rút toàn bộ yêu cầu kháng cáo. Căn cứ Điều 289, Điều 295 của Bộ luật Tố tụng dân sự, QUYẾT ĐỊNH: I, Hủy Bản án hôn nhân và gia đình sơ thẩm số 2382/2024/HNGĐ-ST ngày 11 tháng 6 năm 2024 của Tòa án nhân dân thành phố Thủ Đức, Thành phố Hồ Chí Minh và đình chỉ giải quyết vụ án dân sự phúc thẩm thụ lý số 48/2025/TLPT-HNGĐ ngày 17 tháng 3 năm 2025 về việc “Tranh chấp thay đổi người trực tiếp nuôi con sau khi ly hôn”, giữa: Nguyên đơn: Ông Đặng Vũ Tín, sinh năm 1981.",
    "sentence": null,
    "legal_references": [
      "Bộ luật Tố tụng dân sự, QUYẾT ĐỊNH: I, Hủy Bản án hôn nhân và gia đình sơ thẩm số 2382",
      "Điều 295",
      "Điều 289"
    ],
    "key_facts": []
  },
  "processing_timestamp": "2025-09-23T14:09:15.843677",
  "confidence_score": 0.85
}